send_email_zxx/__init__.py
send_email_zxx/emailLib.py
send_email_zxx-1.0.1.dist-info/LICENSE
send_email_zxx-1.0.1.dist-info/METADATA
send_email_zxx-1.0.1.dist-info/WHEEL
send_email_zxx-1.0.1.dist-info/top_level.txt
send_email_zxx-1.0.1.dist-info/RECORD
