Metadata-Version: 2.1
Name: send_email_zxx
Version: 1.0.1
Summary: 简单的连接邮箱, 生成邮件并发送
Author-email: Zuoxiaoxian <1980179070@qq.com>
Project-URL: Homepage, https://github.com/Zuoxiaoxian/zxx_email
Project-URL: Issues, https://github.com/Zuoxiaoxian/zxx_email/issues
Classifier: Programming Language :: Python :: 3
Classifier: License :: OSI Approved :: MIT License
Classifier: Operating System :: OS Independent
Requires-Python: >=3.7
License-File: LICENSE
